purr_petra/__init__.py
purr_petra/assets/__init__.py
purr_petra/assets/collect/handle_query.py
purr_petra/assets/collect/post_process.py
purr_petra/assets/collect/recipes/core.py
purr_petra/assets/collect/recipes/dst.py
purr_petra/assets/collect/recipes/formation.py
purr_petra/assets/collect/recipes/ip.py
purr_petra/assets/collect/recipes/perforation.py
purr_petra/assets/collect/recipes/production.py
purr_petra/assets/collect/recipes/raster_log.py
purr_petra/assets/collect/recipes/survey.py
purr_petra/assets/collect/recipes/vector_log.py
purr_petra/assets/collect/recipes/well.py
purr_petra/assets/collect/recipes/zone.py
purr_petra/assets/collect/routes_assets.py
purr_petra/assets/collect/sql_helper.py
purr_petra/assets/collect/xformer.py
purr_petra/bin/du64.exe
purr_petra/core/__init__.py
purr_petra/core/crud.py
purr_petra/core/database.py
purr_petra/core/dbisam.py
purr_petra/core/logger.py
purr_petra/core/models.py
purr_petra/core/routes_settings.py
purr_petra/core/schemas.py
purr_petra/core/util.py
purr_petra/main.py
purr_petra/prep/__init__.py
purr_petra/prep/dbodbc.dll
purr_petra/prep/setup.py
purr_petra/recon/__init__.py
purr_petra/recon/epsg.py
purr_petra/recon/recon.py
purr_petra/recon/repo_db.py
purr_petra/recon/repo_fs.py
purr_petra-0.1.5.dist-info/entry_points.txt
purr_petra-0.1.5.dist-info/LICENSE
purr_petra-0.1.5.dist-info/METADATA
purr_petra-0.1.5.dist-info/WHEEL
purr_petra-0.1.5.dist-info/RECORD
